MANIFEST.in
README.md
pyproject.toml
setup.cfg
setup.py
kedro_airflow_k8s/__init__.py
kedro_airflow_k8s/airflow.py
kedro_airflow_k8s/airflow_dag_template.j2
kedro_airflow_k8s/airflow_spark_task_template.j2
kedro_airflow_k8s/cli.py
kedro_airflow_k8s/cli_helper.py
kedro_airflow_k8s/config.py
kedro_airflow_k8s/context_helper.py
kedro_airflow_k8s/dataproc_init_script_template.j2
kedro_airflow_k8s/hooks.py
kedro_airflow_k8s/task_group.py
kedro_airflow_k8s/template.py
kedro_airflow_k8s/template_helper.py
kedro_airflow_k8s.egg-info/PKG-INFO
kedro_airflow_k8s.egg-info/SOURCES.txt
kedro_airflow_k8s.egg-info/dependency_links.txt
kedro_airflow_k8s.egg-info/entry_points.txt
kedro_airflow_k8s.egg-info/not-zip-safe
kedro_airflow_k8s.egg-info/requires.txt
kedro_airflow_k8s.egg-info/top_level.txt
kedro_airflow_k8s/operators/__init__.py
kedro_airflow_k8s/operators/create_pipeline_storage.py
kedro_airflow_k8s/operators/data_volume_init.py
kedro_airflow_k8s/operators/delete_pipeline_storage.py
kedro_airflow_k8s/operators/node_pod.py
kedro_airflow_k8s/operators/spark_submit_k8s.py
kedro_airflow_k8s/operators/start_mlflow_experiment.py
tests/operators/__init__.py
tests/operators/test_create_pipeline_storage_operator.py
tests/operators/test_data_volume_init_operator.py
tests/operators/test_delete_pipeline_storage_operator.py
tests/operators/test_node_pod_operator.py
tests/operators/test_spark_submit_k8s_operator.py
tests/operators/test_start_mlflow_experiment_operator.py