Metadata-Version: 2.1
Name: kedro-airflow-k8s
Version: 0.8.0
Summary: Kedro plugin with Airflow on Kubernetes support
Home-page: https://github.com/getindata/kedro-airflow-k8s/
Author: Michal Zelechowski, Mariusz Strzelecki, Mateusz Pytel
Author-email: mateusz@getindata.com
License: Apache Software License (Apache 2.0)
Keywords: kedro airflow kubernetes k8s ml mlops plugin
Platform: UNKNOWN
Classifier: Development Status :: 4 - Beta
Classifier: Programming Language :: Python :: 3.7
Classifier: Programming Language :: Python :: 3.8
Requires-Python: >=3
Provides-Extra: tests
Provides-Extra: docs
Provides-Extra: gcp
Provides-Extra: aws
Provides-Extra: mlflow
Provides-Extra: spark
